uniseg/__init__.py
uniseg/breaking.py
uniseg/db.py
uniseg/db_lookups.py
uniseg/derived.py
uniseg/emoji.py
uniseg/graphemecluster.py
uniseg/linebreak.py
uniseg/sentencebreak.py
uniseg/unicodedatawrapper.py
uniseg/unicodeproperty.py
uniseg/wordbreak.py
uniseg/wrap.py
uniseg/docs/html/codepoint.html
uniseg/docs/html/genindex.html
uniseg/docs/html/graphemecluster.html
uniseg/docs/html/index.html
uniseg/docs/html/introduction.html
uniseg/docs/html/license.html
uniseg/docs/html/linebreak.html
uniseg/docs/html/modules.html
uniseg/docs/html/py-modindex.html
uniseg/docs/html/samples.html
uniseg/docs/html/search.html
uniseg/docs/html/searchindex.js.tmp
uniseg/docs/html/sentencebreak.html
uniseg/docs/html/unibreak.html
uniseg/docs/html/uniwrap.html
uniseg/docs/html/wordbreak.html
uniseg/docs/html/wrap.html
uniseg/docs/html/wxwrapdemo.html
uniseg/docs/html/_images/wxwrapdemo-osx.png
uniseg/docs/html/_images/wxwrapdemo-ubuntu.png
uniseg/docs/html/_images/wxwrapdemo-windows.png
uniseg/docs/html/_sources/codepoint.rst.txt
uniseg/docs/html/_sources/graphemecluster.rst.txt
uniseg/docs/html/_sources/index.rst.txt
uniseg/docs/html/_sources/introduction.rst.txt
uniseg/docs/html/_sources/license.rst.txt
uniseg/docs/html/_sources/linebreak.rst.txt
uniseg/docs/html/_sources/modules.rst.txt
uniseg/docs/html/_sources/samples.rst.txt
uniseg/docs/html/_sources/sentencebreak.rst.txt
uniseg/docs/html/_sources/unibreak.rst.txt
uniseg/docs/html/_sources/uniwrap.rst.txt
uniseg/docs/html/_sources/wordbreak.rst.txt
uniseg/docs/html/_sources/wrap.rst.txt
uniseg/docs/html/_sources/wxwrapdemo.rst.txt
uniseg/docs/html/_static/_sphinx_javascript_frameworks_compat.js
uniseg/docs/html/_static/basic.css
uniseg/docs/html/_static/doctools.js
uniseg/docs/html/_static/documentation_options.js
uniseg/docs/html/_static/file.png
uniseg/docs/html/_static/jquery.js
uniseg/docs/html/_static/language_data.js
uniseg/docs/html/_static/minus.png
uniseg/docs/html/_static/plus.png
uniseg/docs/html/_static/pygments.css
uniseg-0.10.1.dist-info/licenses/LICENSE
uniseg-0.10.1.dist-info/METADATA
uniseg-0.10.1.dist-info/WHEEL
uniseg-0.10.1.dist-info/top_level.txt
uniseg-0.10.1.dist-info/RECORD
